{
  "type": "minecraft:block_column",
  "config": {
    "allowed_placement": {
      "type": "minecraft:matching_blocks",
      "blocks": "minecraft:air"
    },
    "direction": "up",
    "layers": [
      {
        "height": {
          "type": "uniform",
          "value": {
            "min_inclusive": 3,
            "max_inclusive": 7
          }
        },
        "provider": {
          "type": "minecraft:simple_state_provider",
          "state": {
            "Name": "tstp_content:cactus"
          }
        }
      }
    ],
    "prioritize_tip": false
  }
}